topoconvert/__init__.py
topoconvert/__main__.py
topoconvert/cli.py
topoconvert/commands/__init__.py
topoconvert/commands/csv_to_kml.py
topoconvert/commands/gps_grid.py
topoconvert/commands/kml_contours_to_dxf.py
topoconvert/commands/kml_to_contours.py
topoconvert/commands/kml_to_mesh.py
topoconvert/commands/kml_to_points.py
topoconvert/commands/multi_csv_to_dxf.py
topoconvert/commands/multi_csv_to_kml.py
topoconvert/commands/slope_heatmap.py
topoconvert/core/__init__.py
topoconvert/core/combined_dxf.py
topoconvert/core/combined_kml.py
topoconvert/core/contours.py
topoconvert/core/csv_kml.py
topoconvert/core/exceptions.py
topoconvert/core/gps_grid.py
topoconvert/core/kml_contours.py
topoconvert/core/mesh.py
topoconvert/core/points.py
topoconvert/core/result_types.py
topoconvert/core/slope_heatmap.py
topoconvert/core/utils.py
topoconvert/utils/__init__.py
topoconvert/utils/projection.py
topoconvert-0.1.3.dist-info/licenses/LICENSE
topoconvert-0.1.3.dist-info/METADATA
topoconvert-0.1.3.dist-info/WHEEL
topoconvert-0.1.3.dist-info/entry_points.txt
topoconvert-0.1.3.dist-info/top_level.txt
topoconvert-0.1.3.dist-info/RECORD
