Metadata-Version: 2.4
Name: topoconvert
Version: 0.1.3
Summary: A Python CLI tool for converting geospatial survey data between KML, CSV, and DXF formats with specialized topographical operations
Author-email: David Garcia <dgarcia182@gmail.com>
Maintainer-email: David Garcia <dgarcia182@gmail.com>
License: MIT
Project-URL: Homepage, https://github.com/DavGarcia/topoconvert
Project-URL: Documentation, https://github.com/DavGarcia/topoconvert#readme
Project-URL: Repository, https://github.com/DavGarcia/topoconvert.git
Project-URL: Bug Tracker, https://github.com/DavGarcia/topoconvert/issues
Keywords: geospatial,gis,survey,topographical,kml,csv,dxf,conversion,cli,mapping,coordinates,elevation,contours,mesh,gps,surveying,cad,autocad,geodata
Classifier: Development Status :: 3 - Alpha
Classifier: Intended Audience :: Developers
Classifier: Intended Audience :: Science/Research
Classifier: Operating System :: OS Independent
Classifier: Programming Language :: Python :: 3
Classifier: Programming Language :: Python :: 3.9
Classifier: Programming Language :: Python :: 3.10
Classifier: Programming Language :: Python :: 3.11
Classifier: Programming Language :: Python :: 3.12
Classifier: Topic :: Scientific/Engineering :: GIS
Requires-Python: >=3.9
License-File: LICENSE
Requires-Dist: shapely>=2.0.0
Requires-Dist: pandas>=1.5.0
Requires-Dist: ezdxf>=1.0.0
Requires-Dist: pyproj>=3.4.0
Requires-Dist: scipy>=1.10.0
Requires-Dist: numpy>=1.24.0
Requires-Dist: matplotlib>=3.6.0
Requires-Dist: alphashape>=1.3.0
Requires-Dist: concave_hull>=0.0.7
Requires-Dist: click>=8.1.0
Requires-Dist: tomli>=1.2.0; python_version < "3.11"
Provides-Extra: dev
Requires-Dist: pytest>=7.2.0; extra == "dev"
Requires-Dist: pytest-cov>=4.0.0; extra == "dev"
Requires-Dist: pytest-benchmark>=4.0.0; extra == "dev"
Requires-Dist: hypothesis>=6.68.0; extra == "dev"
Requires-Dist: psutil>=5.9.0; extra == "dev"
Requires-Dist: black>=23.0.0; extra == "dev"
Requires-Dist: flake8>=6.0.0; extra == "dev"
Requires-Dist: mypy>=1.0.0; extra == "dev"
Requires-Dist: pre-commit>=3.0.0; extra == "dev"
Provides-Extra: docs
Requires-Dist: sphinx>=5.0.0; extra == "docs"
Requires-Dist: sphinx-rtd-theme>=1.2.0; extra == "docs"
Requires-Dist: myst-parser>=0.18.0; extra == "docs"
Provides-Extra: tools
Requires-Dist: ipython>=8.0.0; extra == "tools"
Requires-Dist: jupyter>=1.0.0; extra == "tools"
Requires-Dist: notebook>=6.5.0; extra == "tools"
Dynamic: license-file
